setup.py
TracDeveloper.egg-info/PKG-INFO
TracDeveloper.egg-info/SOURCES.txt
TracDeveloper.egg-info/dependency_links.txt
TracDeveloper.egg-info/entry_points.txt
TracDeveloper.egg-info/top_level.txt
tracdeveloper/__init__.py
tracdeveloper/apidoc.py
tracdeveloper/debugger.py
tracdeveloper/javascript.py
tracdeveloper/log.py
tracdeveloper/main.py
tracdeveloper/plugins.py
tracdeveloper/util.py
tracdeveloper/dozer/LICENSE
tracdeveloper/dozer/__init__.py
tracdeveloper/dozer/reftree.py
tracdeveloper/dozer/htdocs/excanvas.compiled.js
tracdeveloper/dozer/htdocs/jspark.js
tracdeveloper/dozer/htdocs/main.css
tracdeveloper/dozer/templates/graphs.html
tracdeveloper/dozer/templates/trace.html
tracdeveloper/dozer/templates/tree.html
tracdeveloper/htdocs/css/apidoc.css
tracdeveloper/htdocs/css/debugger.css
tracdeveloper/htdocs/css/plugins.css
tracdeveloper/htdocs/js/apidoc.js
tracdeveloper/htdocs/js/debugger.js
tracdeveloper/htdocs/js/jquery-1.2.1.js
tracdeveloper/htdocs/js/jquery-1.2.6.js
tracdeveloper/htdocs/js/log.js
tracdeveloper/htdocs/js/plugins.js
tracdeveloper/templates/developer/apidoc.html
tracdeveloper/templates/developer/debug.html
tracdeveloper/templates/developer/debug_help.html
tracdeveloper/templates/developer/debug_node.html
tracdeveloper/templates/developer/index.html
tracdeveloper/templates/developer/plugins.html
tracdeveloper/templates/developer/prefs_developer.html