Metadata-Version: 1.0
Name: TracDeveloper
Version: 0.2
Summary: Adds some features to Trac that are useful for developers
Home-page: http://trac-hacks.org/wiki/TracDeveloperPlugin
Author: Alec Thomas
Author-email: UNKNOWN
License: BSD
Platform: UNKNOWN
